inichord_GPUindex/__init__.py
inichord_GPUindex/Aligned_pg_ui_12_TSG.ui
inichord_GPUindex/Alignement_GUI_pg_11_TSG.py
inichord_GPUindex/Batch_processing_01.py
inichord_GPUindex/Batch_processing_ui_01.ui
inichord_GPUindex/BM3D_GUI_pg_v2_TSG.py
inichord_GPUindex/BM3D_v2_TSG.ui
inichord_GPUindex/Denoise_2Dmap_01.py
inichord_GPUindex/Denoise_2Dmap_ui_01.ui
inichord_GPUindex/Denoise_GUI_pg_03_TSG.py
inichord_GPUindex/Denoise_v1.ui
inichord_GPUindex/Extract_mosaic_acquisition_01.py
inichord_GPUindex/Extract_mosaic_ui_01.ui
inichord_GPUindex/Fct_profil_modification_02.py
inichord_GPUindex/general_functions.py
inichord_GPUindex/GrainTreatment_06_GUI_TSG.py
inichord_GPUindex/GrainTreatment_v5_TSG.ui
inichord_GPUindex/Indexation_04_GUI_TSG.py
inichord_GPUindex/indexation_tiff_sur_GPU_v27_lib_TSG.py
inichord_GPUindex/Indexation_v2_TSG.ui
inichord_GPUindex/IPF_V2_TSG.py
inichord_GPUindex/KAD_function_02.py
inichord_GPUindex/NLMD_GUI_pg_v2_TSG.py
inichord_GPUindex/NLMD_v2_TSG.ui
inichord_GPUindex/remFFT_pg_v2_TSG.py
inichord_GPUindex/remOutliers_v4_TSG.ui
inichord_GPUindex/remOutliersGUI_pg_v3_TSG.py
inichord_GPUindex/RemovedFFT_v2_TSG.ui
inichord_GPUindex/Restored_01_GUI_TSG.py
inichord_GPUindex/Restored_v1_TSG.ui
inichord_GPUindex/Series_Stitching_v4.ui
inichord_GPUindex/stackModifier_v9_TSG.ui
inichord_GPUindex/stackModifierGUI_pg_v7_TSG.py
inichord_GPUindex/Stitching_v4.ui
inichord_GPUindex/Symetry.py
inichord_GPUindex/ThreeD_Stitching_02_GUI.py
inichord_GPUindex/Traitement_stack_12_GUI.py
inichord_GPUindex/Traitement_stack_v12.ui
inichord_GPUindex/TwoD_Stitching_04_GUI.py
inichord_GPUindex/VSNR_GUI_pg_v2_TSG.py
inichord_GPUindex/VSNR_v2_TSG.ui
inichord_GPUindex/Xallo.py
inichord_gpuindex-0.1.11.dist-info/entry_points.txt
inichord_gpuindex-0.1.11.dist-info/LICENSE
inichord_gpuindex-0.1.11.dist-info/METADATA
inichord_gpuindex-0.1.11.dist-info/WHEEL
inichord_gpuindex-0.1.11.dist-info/RECORD
